ASecondCourseInAlgorithmsLectureNotesStanfordCs261/README.md
ASecondCourseInAlgorithmsLectureNotesStanfordCs261/__init__.py
ASecondCourseInAlgorithmsLectureNotesStanfordCs261/__main__.py
ASecondCourseInAlgorithmsLectureNotesStanfordCs261/file.pdf
ASecondCourseInAlgorithmsLectureNotesStanfordCs261/index.html
a_second_course_in_algorithms_lecture_notes_stanford_cs261-2024.3.1.0.dist-info/METADATA
a_second_course_in_algorithms_lecture_notes_stanford_cs261-2024.3.1.0.dist-info/WHEEL
a_second_course_in_algorithms_lecture_notes_stanford_cs261-2024.3.1.0.dist-info/entry_points.txt
a_second_course_in_algorithms_lecture_notes_stanford_cs261-2024.3.1.0.dist-info/top_level.txt
a_second_course_in_algorithms_lecture_notes_stanford_cs261-2024.3.1.0.dist-info/RECORD
